{
    "Data": [
        {
            "CCTV" : "CCTV1",
            "관제사" : "김개똥",
            "이벤트타입" : "교통관제",
            "처리상황" : "이상없음"
        },
        {
            "CCTV" : "CCTV2",
            "관제사" : "김개똥",
            "이벤트타입" : "무전취식",
            "처리상황" : "이상없음"
        },
        {
            "CCTV" : "CCTV3",
            "관제사" : "김개똥",
            "이벤트타입" : "무전취식",
            "처리상황" : "이상없음"
        },
        {
            "CCTV" : "CCTV4",
            "관제사" : "나개똥",
            "이벤트타입" : "무전취식",
            "처리상황" : "이상없음"
        },
        {
            "CCTV" : "CCTV5",
            "관제사" : "다개똥",
            "이벤트타입" : "무전취식",
            "처리상황" : "이상없음"
        }
       
    ]
}